LICENSE
README.md
pyproject.toml
runtime_builder.py
setup.py
runtime_builder.egg-info/PKG-INFO
runtime_builder.egg-info/SOURCES.txt
runtime_builder.egg-info/dependency_links.txt
runtime_builder.egg-info/requires.txt
runtime_builder.egg-info/top_level.txt
tests/test_builder.py