Metadata-Version: 2.1
Name: runtime_builder
Version: 0.1.5
Summary: Allow automatic builds in edit mode
Author-email: Richard Kiss <him@richardkiss.com>
License: Copyright 2023 by Richard Kiss
License-File: LICENSE
Requires-Dist: importlib_resources>=6.1.1
